{
    "content":{
        "q1":{
            "imgSrc":"https://gma.alicdn.com/bao/uploaded/i2/16108533/O1CN01edt0ZS2CuA6bebvW4_!!0-saturn_solar.jpg_200x200.jpg_.webp",
            "imgSrc1":"https://gma.alicdn.com/bao/uploaded/i2/16108533/O1CN01edt0ZS2CuA6bebvW4_!!0-saturn_solar.jpg_200x200.jpg_.webp",
            "title":"阿芙精油口红唇膏",
            "price":"89.2",
            "id":"q1"
        },
        "q2":{
            "imgSrc":"https://gma.alicdn.com/bao/uploaded/i1/130943634/O1CN01DA8D0j1ciPqAo79PJ_!!0-saturn_solar.jpg_200x200.jpg_.webp",
            "imgSrc1":"https://gma.alicdn.com/bao/uploaded/i1/130943634/O1CN01DA8D0j1ciPqAo79PJ_!!0-saturn_solar.jpg_200x200.jpg_.webp",
            "title":"YSL圣罗兰纯口红 方管正红色1星星色52正橘",
            "price":"320.5",
            "id":"q2"
        }, 
        "q3":{
            "imgSrc":"https://gma.alicdn.com/bao/uploaded/i3/118860163/O1CN01Exy4eJ1D4h3Dx7asr_!!0-saturn_solar.jpg_200x200.jpg_.webp",
            "imgSrc1":"https://gma.alicdn.com/bao/uploaded/i3/118860163/O1CN01Exy4eJ1D4h3Dx7asr_!!0-saturn_solar.jpg_200x200.jpg_.webp",
            "title":"雨伞全自动两用折叠大码双层个性创意雨伞",
            "price":"109",
            "id":"q3"
        },
        "q4":{
            "imgSrc":"https://gma.alicdn.com/bao/uploaded/i4/118013231/O1CN01gkIjkw1ZjqBxrLVRx_!!0-saturn_solar.jpg_200x200.jpg_.webp",
            "imgSrc11":"https://gma.alicdn.com/bao/uploaded/i4/118013231/O1CN01gkIjkw1ZjqBxrLVRx_!!0-saturn_solar.jpg_200x200.jpg_.webp",
            "title":"陕西西安手工小麻花特产散装网红海苔味",
            "price":"29.9",
            "id":"q4"
        },
        "q5":{
            "imgSrc":"http://img.alicdn.com/bao/uploaded/i4/121456159/O1CN01X4AxiN1vMruAtvl1G_!!0-saturn_solar.jpg_400x400q90.jpg_.webp",
            "imgSrc1":"http://img.alicdn.com/bao/uploaded/i4/121456159/O1CN01X4AxiN1vMruAtvl1G_!!0-saturn_solar.jpg_400x400q90.jpg_.webp",
            "title":"预售献礼MAC/魅可全色号子弹头唇膏 哑光口",
            "price":"170",
            "id":"q5"
        },
        "q6":{
            "imgSrc":"https://img.alicdn.com/bao/uploaded/i2/167010366/TB2YLnVhb1YBuNjSszhXXcUsFXa_!!167010366.jpg_400x400q90.jpg_.webp",
            "imgSrc1":"https://img.alicdn.com/bao/uploaded/i2/167010366/TB2YLnVhb1YBuNjSszhXXcUsFXa_!!167010366.jpg_400x400q90.jpg_.webp",
            "title":"理想三旬复古蓝汉服重工蕾丝宽松休闲仙女披肩长开衫两件套",
            "price":"145",
            "id":"q6"
        },
        "q7":{
            "imgSrc":"http://img.alicdn.com/bao/uploaded/i4/121456159/O1CN01MkMUt41vMru5VTCYH_!!0-saturn_solar.jpg_400x400q90.jpg_.webp",
            "imgSrc1":"http://img.alicdn.com/bao/uploaded/i4/121456159/O1CN01MkMUt41vMru5VTCYH_!!0-saturn_solar.jpg_400x400q90.jpg_.webp",
            "title":"年度新品MAC/魅可丝缎柔雾唇膏/口红磨砂系",
            "price":"170",
            "id":"q7"
        },
        "q8":{
            "imgSrc":"http://img.alicdn.com/bao/uploaded/i4/1676486019/TB15g.IX5qAXuNjy1XdXXaYcVXa_!!0-item_pic.jpg_400x400q90.jpg_.webp",
            "imgSrc1":"http://img.alicdn.com/bao/uploaded/i4/1676486019/TB15g.IX5qAXuNjy1XdXXaYcVXa_!!0-item_pic.jpg_400x400q90.jpg_.webp",
            "title":"曼轻罗2019复古唯美飘逸大摆绣花开衫系带百搭防晒衣 轻薄外套",
            "price":"90",
            "id":"q8"
        },
        "q9":{
            "imgSrc":"http://img.alicdn.com/bao/uploaded/i2/703411621/TB2eBjBcPm2.eBjSZFtXXX56VXa_!!703411621.jpg_400x400q90.jpg_.webp",
            "imgSrc1":"http://img.alicdn.com/bao/uploaded/i2/703411621/TB2eBjBcPm2.eBjSZFtXXX56VXa_!!703411621.jpg_400x400q90.jpg_.webp",
            "title":"很重工！现货~春秋 复刻 清仓款 极乐天 凤凰刺绣外套 大袖衫",
            "price":"150",
            "id":"q9"
        },
        "q10":{
            "imgSrc":"http://img.alicdn.com/bao/uploaded/i2/69644597/TB2KGNPlCBjpuFjy1XdXXaooVXa_!!69644597.jpg_400x400q90.jpg_.webp",
            "imgSrc1":"http://img.alicdn.com/bao/uploaded/i2/69644597/TB2KGNPlCBjpuFjy1XdXXaooVXa_!!69644597.jpg_400x400q90.jpg_.webp",
            "title":"棉麻记2019夏装新款复古汉服长裙飘带大摆修身连衣裙大广袖女裙子",
            "price":"198",
            "id":"q10"
        },
        "q11":{
            "imgSrc":"https://gma.alicdn.com/bao/uploaded/i1/130943634/O1CN01DA8D0j1ciPqAo79PJ_!!0-saturn_solar.jpg_200x200.jpg_.webp",
            "imgSrc1":"https://gma.alicdn.com/bao/uploaded/i1/130943634/O1CN01DA8D0j1ciPqAo79PJ_!!0-saturn_solar.jpg_200x200.jpg_.webp",
            "title":"YSL圣罗兰纯口红 方管正红色1星星色52正橘",
            "price":"320",
            "id":"q11"
        },
        "q12":{
            "imgSrc":"https://gma.alicdn.com/bao/uploaded/i3/118860163/O1CN01Exy4eJ1D4h3Dx7asr_!!0-saturn_solar.jpg_200x200.jpg_.webp",
            "imgSrc1":"https://gma.alicdn.com/bao/uploaded/i3/118860163/O1CN01Exy4eJ1D4h3Dx7asr_!!0-saturn_solar.jpg_200x200.jpg_.webp",
            "title":"雨伞全自动两用折叠大码双层个性创意雨伞",
            "price":"109",
            "id":"q12"
        },
        "q13":{
            "imgSrc":"https://gma.alicdn.com/bao/uploaded/i4/118013231/O1CN01gkIjkw1ZjqBxrLVRx_!!0-saturn_solar.jpg_200x200.jpg_.webp",
            "imgSrc1":"https://gma.alicdn.com/bao/uploaded/i4/118013231/O1CN01gkIjkw1ZjqBxrLVRx_!!0-saturn_solar.jpg_200x200.jpg_.webp",
            "title":"陕西西安手工小麻花特产散装网红海苔味",
            "price":"29.9",
            "id":"q13"
        },
        "q14":{
            "imgSrc":"http://img.alicdn.com/bao/uploaded/i4/121456159/O1CN01X4AxiN1vMruAtvl1G_!!0-saturn_solar.jpg_400x400q90.jpg_.webp",
            "imgSrc1":"http://img.alicdn.com/bao/uploaded/i4/121456159/O1CN01X4AxiN1vMruAtvl1G_!!0-saturn_solar.jpg_400x400q90.jpg_.webp",
            "title":"预售献礼MAC/魅可全色号子弹头唇膏 哑光口",
            "price":"170",
            "id":"q14"
        },
        "q15":{
            "imgSrc":"https://img.alicdn.com/bao/uploaded/i2/167010366/TB2YLnVhb1YBuNjSszhXXcUsFXa_!!167010366.jpg_400x400q90.jpg_.webp",
            "imgSrc1":"https://img.alicdn.com/bao/uploaded/i2/167010366/TB2YLnVhb1YBuNjSszhXXcUsFXa_!!167010366.jpg_400x400q90.jpg_.webp",
            "title":"理想三旬复古蓝汉服重工蕾丝宽松休闲仙女披肩长开衫两件套",
            "price":"145",
            "id":"q15"
        },
        "q16":{
            "imgSrc":"http://img.alicdn.com/bao/uploaded/i4/121456159/O1CN01MkMUt41vMru5VTCYH_!!0-saturn_solar.jpg_400x400q90.jpg_.webp",
            "imgSrc1":"http://img.alicdn.com/bao/uploaded/i4/121456159/O1CN01MkMUt41vMru5VTCYH_!!0-saturn_solar.jpg_400x400q90.jpg_.webp",
            "title":"年度新品MAC/魅可丝缎柔雾唇膏/口红磨砂系",
            "price":"170",
            "id":"q16"
        },
        "q17":{
            "imgSrc":"http://img.alicdn.com/bao/uploaded/i4/1676486019/TB15g.IX5qAXuNjy1XdXXaYcVXa_!!0-item_pic.jpg_400x400q90.jpg_.webp",
            "imgSrc1":"http://img.alicdn.com/bao/uploaded/i4/1676486019/TB15g.IX5qAXuNjy1XdXXaYcVXa_!!0-item_pic.jpg_400x400q90.jpg_.webp",
            "title":"曼轻罗2019复古唯美飘逸大摆绣花开衫系带百搭防晒衣 轻薄外套",
            "price":"90",
            "id":"q17"
        },
        "q18":{
            "imgSrc":"http://img.alicdn.com/bao/uploaded/i2/703411621/TB2eBjBcPm2.eBjSZFtXXX56VXa_!!703411621.jpg_400x400q90.jpg_.webp",
            "imgSrc1":"http://img.alicdn.com/bao/uploaded/i2/703411621/TB2eBjBcPm2.eBjSZFtXXX56VXa_!!703411621.jpg_400x400q90.jpg_.webp",
            "title":"很重工！现货~春秋 复刻 清仓款 极乐天 凤凰刺绣外套 大袖衫",
            "price":"150",
            "id":"q18"
        },
        "q19":{
            "imgSrc":"http://img.alicdn.com/bao/uploaded/i2/69644597/TB2KGNPlCBjpuFjy1XdXXaooVXa_!!69644597.jpg_400x400q90.jpg_.webp",
            "imgSrc1":"http://img.alicdn.com/bao/uploaded/i2/69644597/TB2KGNPlCBjpuFjy1XdXXaooVXa_!!69644597.jpg_400x400q90.jpg_.webp",
            "title":"棉麻记2019夏装新款复古汉服长裙飘带大摆修身连衣裙大广袖女裙子",
            "price":"198",
            "id":"q19"
        }


        
        
    }
}